samtariFirstPackage/__init__.py
samtariFirstPackage/add.py
samtariFirstPackage/main.py
samtariFirstPackage/sub.py
samtariFirstPackage/extras/__init__.py
samtariFirstPackage/extras/divide.py
samtariFirstPackage/extras/multiply.py
samtariFirstPackage-0.1.9.dist-info/METADATA
samtariFirstPackage-0.1.9.dist-info/WHEEL
samtariFirstPackage-0.1.9.dist-info/top_level.txt
samtariFirstPackage-0.1.9.dist-info/RECORD
