Metadata-Version: 2.1
Name: samtariFirstPackage
Version: 0.1.9
Summary: My first Python package
Author: Sam Yang
Author-email: samtari@163.com
License: UNKNOWN
Keywords: python,first package
Platform: UNKNOWN
Classifier: Development Status :: 3 - Alpha
Classifier: Intended Audience :: Education
Classifier: Programming Language :: Python :: 2
Classifier: Programming Language :: Python :: 3
Classifier: Operating System :: MacOS :: MacOS X
Classifier: Operating System :: Microsoft :: Windows
